Leveler/Leveler.py
Leveler/__init__.py
Leveler-0.1.5.dist-info/METADATA
Leveler-0.1.5.dist-info/WHEEL
Leveler-0.1.5.dist-info/top_level.txt
Leveler-0.1.5.dist-info/RECORD
